biobrary/__init__.py
biobrary/misc.py
biobrary/seq.py
biobrary/bioparse/__init__.py
biobrary/bioparse/fasta.py
biobrary/bioparse/gtf.py
biobrary/data/__init__.py
biobrary/data/base_complement.py
biobrary/data/biocodon.py
biobrary/data/molecular_weight.py
biobrary/data/score_matrix.py
biobrary/tree/CircleNode.py
biobrary/tree/__init__.py
biobrary-0.2.5.dist-info/LICENSE
biobrary-0.2.5.dist-info/METADATA
biobrary-0.2.5.dist-info/WHEEL
biobrary-0.2.5.dist-info/top_level.txt
biobrary-0.2.5.dist-info/RECORD
