Metadata-Version: 2.1
Name: biobrary
Version: 0.2.5
Summary: A library for biological computing works
Author-email: Hailing Fang <hailing.fang@outlook.com>
License: MIT License
Project-URL: Homepage, https://github.com/hailingfang/biobrary
Keywords: biobrary,bioparse,tree
Classifier: Programming Language :: Python :: 3
Requires-Python: >=3.7
License-File: LICENSE
Requires-Dist: ete3>=3.1.1
Requires-Dist: numpy>=1.21.2
Requires-Dist: six>=1.15.0
